webeye/__init__.py
webeye/__main__.py
webeye/core.py
webeye/encryptions/__init__.py
webeye/encryptions/rot.py
webeye-2.3.12.dist-info/LICENSE
webeye-2.3.12.dist-info/METADATA
webeye-2.3.12.dist-info/WHEEL
webeye-2.3.12.dist-info/entry_points.txt
webeye-2.3.12.dist-info/top_level.txt
webeye-2.3.12.dist-info/RECORD
