Metadata-Version: 2.1
Name: webeye
Version: 2.3.12
Summary: A Best Powerful module for making ethical hacking tools easier
Home-page: https://github.com/Zaeem20/webeye
Author: Zaeem Technical
Author-email: business@zaeemtechnical.ml
License: MIT
Keywords: webeye red_hawk nikto webrecon recondog
Classifier: License :: OSI Approved :: MIT License
Classifier: Environment :: Web Environment
Classifier: Intended Audience :: Developers
Classifier: Natural Language :: English
Classifier: Operating System :: OS Independent
Classifier: Programming Language :: Python :: 3.8
Classifier: Programming Language :: Python :: 3.7
Classifier: Programming Language :: Python :: 3.6
Requires-Python: >=3.6
License-File: LICENSE
Requires-Dist: requests (>=2)
Requires-Dist: httpx (==0.20.0)
Requires-Dist: mechanize (==0.4.7)
Requires-Dist: beautifulsoup4 (==4.10.0)
